ataskq/__init__.py
ataskq/__main__.py
ataskq/conftest.py
ataskq/env.py
ataskq/imodel.py
ataskq/logger.py
ataskq/models.py
ataskq/monitor.py
ataskq/taskq.py
ataskq/test_0.py
ataskq/test_ataskq.py
ataskq/test_config.py
ataskq/test_handler.py
ataskq/test_main.py
ataskq/test_models.py
ataskq/test_queries.py
ataskq/version.py
ataskq/config/__init__.py
ataskq/config/config.py
ataskq/config/load.py
ataskq/handler/__init__.py
ataskq/handler/db_handler.py
ataskq/handler/handler.py
ataskq/handler/postgresql.py
ataskq/handler/rest_handler.py
ataskq/handler/sqlite3.py
ataskq/server/background.py
ataskq/server/form_utils.py
ataskq/server/server.py
ataskq/server/www/ataskq-32.png
ataskq/server/www/favicon.ico
ataskq/server/www/index.html
ataskq/server/www/version.txt
ataskq/server/www/assets/index-MiCEdQXI.js
ataskq/server/www/assets/index-MiCEdQXI.js.map
ataskq/server/www/assets/index-_NWmBfbC.css
ataskq/tasks_utils/__init__.py
ataskq/tasks_utils/counter_task.py
ataskq/tasks_utils/write_to_file_tasks.py
ataskq-6.0.0.dist-info/LICENSE
ataskq-6.0.0.dist-info/METADATA
ataskq-6.0.0.dist-info/WHEEL
ataskq-6.0.0.dist-info/top_level.txt
ataskq-6.0.0.dist-info/RECORD
