Metadata-Version: 2.1
Name: ataskq
Version: 6.0.0
Summary: Easily create and run tasks (=function calls) with almost seamless transition between Local development and Distributed deployment.
Project-URL: Homepage, https://github.com/innoviz-swt/a-task-queue
Project-URL: Issues, https://github.com/innoviz-swt/a-task-queue/issues
Keywords: python,task,queue,distributed systems,distributed computing
Classifier: Programming Language :: Python :: 3
Classifier: License :: OSI Approved :: MIT License
Classifier: Operating System :: OS Independent
Requires-Python: >=3.8
License-File: LICENSE
